{
	"storyName": "FREEDOOM",
	"difficulties": "Normal",
	"hideFreeplay": false,
	"weekBackground": "",
	"weekBefore": "tutorial",
	"freeplayColor": [
		146,
		113,
		253
	],
	"startUnlocked": true,
	"hideStoryMode": false,
	"songs": [
		[
			"D_RUNNIN",
			"dad",
			[
				0,
				20,
				0
			]
		],
		[
			"D_COUNTD",
			"dad",
			[
				0,
				20,
				0
			]
		],
		[
			"D_THE_DA",
			"dad",
			[
				0,
				20,
				0
			]
		]
	],
	"weekCharacters": [
		"dad",
		"bf",
		"gf"
	],
	"hiddenUntilUnlocked": false,
	"weekName": "FreeDoom"
}